[{"anonymous":false,"inputs":[{"indexed":true,"internalType":"uint256","name":"consignmentId","type":"uint256"}],"name":"AuctionExtended","type":"event"},{"anonymous":false,"inputs":[{"indexed":true,"internalType":"uint256","name":"consignmentId","type":"uint256"}],"name":"AuctionStarted","type":"event"},{"anonymous":false,"inputs":[{"indexed":true,"internalType":"uint256","name":"consignmentId","type":"uint256"},{"indexed":true,"internalType":"enum SeenTypes.Audience","name":"audience","type":"uint8"}],"name":"AudienceChanged","type":"event"},{"anonymous":false,"inputs":[{"indexed":true,"internalType":"uint256","name":"consignmentId","type":"uint256"},{"indexed":true,"internalType":"address","name":"buyer","type":"address"},{"indexed":false,"internalType":"uint256","name":"bid","type":"uint256"}],"name":"BidAccepted","type":"event"},{"anonymous":false,"inputs":[{"indexed":true,"internalType":"uint256","name":"consignmentId","type":"uint256"},{"indexed":true,"internalType":"address","name":"buyer","type":"address"},{"indexed":false,"internalType":"uint256","name":"bid","type":"uint256"}],"name":"BidReturned","type":"event"},{"anonymous":false,"inputs":[{"indexed":true,"internalType":"uint256","name":"consignmentId","type":"uint256"},{"indexed":true,"internalType":"address","name":"recipient","type":"address"},{"indexed":false,"internalType":"uint256","name":"amount","type":"uint256"}],"name":"EscrowAgentFeeDisbursed","type":"event"},{"anonymous":false,"inputs":[{"indexed":true,"internalType":"address","name":"recipient","type":"address"},{"indexed":false,"internalType":"uint256","name":"amount","type":"uint256"}],"name":"EthCredited","type":"event"},{"anonymous":false,"inputs":[{"indexed":true,"internalType":"uint256","name":"consignmentId","type":"uint256"},{"indexed":true,"internalType":"address","name":"recipient","type":"address"},{"indexed":false,"internalType":"uint256","name":"amount","type":"uint256"}],"name":"FeeDisbursed","type":"event"},{"anonymous":false,"inputs":[{"indexed":true,"internalType":"uint256","name":"consignmentId","type":"uint256"},{"indexed":true,"internalType":"address","name":"recipient","type":"address"},{"indexed":false,"internalType":"uint256","name":"amount","type":"uint256"}],"name":"PayoutDisbursed","type":"event"},{"anonymous":false,"inputs":[{"indexed":true,"internalType":"uint256","name":"consignmentId","type":"uint256"},{"indexed":true,"internalType":"address","name":"recipient","type":"address"},{"indexed":false,"internalType":"uint256","name":"amount","type":"uint256"}],"name":"RoyaltyDisbursed","type":"event"},{"inputs":[{"internalType":"uint256","name":"_consignmentId","type":"uint256"}],"name":"bid","outputs":[],"stateMutability":"payable","type":"function"},{"inputs":[{"internalType":"uint256","name":"_consignmentId","type":"uint256"},{"internalType":"enum SeenTypes.Audience","name":"_audience","type":"uint8"}],"name":"changeAuctionAudience","outputs":[],"stateMutability":"nonpayable","type":"function"},{"inputs":[],"name":"extensionWindow","outputs":[{"internalType":"uint256","name":"","type":"uint256"}],"stateMutability":"view","type":"function"},{"inputs":[],"name":"initialize","outputs":[],"stateMutability":"nonpayable","type":"function"}]